odoo/addons/maintenance_stock/README.rst
odoo/addons/maintenance_stock/__init__.py
odoo/addons/maintenance_stock/__manifest__.py
odoo/addons/maintenance_stock/hooks.py
odoo/addons/maintenance_stock/data/demo_maintenance_stock.xml
odoo/addons/maintenance_stock/i18n/es.po
odoo/addons/maintenance_stock/i18n/it.po
odoo/addons/maintenance_stock/i18n/maintenance_stock.pot
odoo/addons/maintenance_stock/i18n/pt_BR.po
odoo/addons/maintenance_stock/models/__init__.py
odoo/addons/maintenance_stock/models/maintenance_equipment.py
odoo/addons/maintenance_stock/models/maintenance_request.py
odoo/addons/maintenance_stock/models/stock_move.py
odoo/addons/maintenance_stock/models/stock_move_line.py
odoo/addons/maintenance_stock/models/stock_picking.py
odoo/addons/maintenance_stock/models/stock_warehouse.py
odoo/addons/maintenance_stock/readme/CONTRIBUTORS.rst
odoo/addons/maintenance_stock/readme/DESCRIPTION.rst
odoo/addons/maintenance_stock/readme/ROADMAP.rst
odoo/addons/maintenance_stock/readme/USAGE.rst
odoo/addons/maintenance_stock/static/description/equipment.png
odoo/addons/maintenance_stock/static/description/icon.png
odoo/addons/maintenance_stock/static/description/index.html
odoo/addons/maintenance_stock/static/description/move-line.png
odoo/addons/maintenance_stock/static/description/pick-1.png
odoo/addons/maintenance_stock/static/description/pick-2.png
odoo/addons/maintenance_stock/static/description/request-1.png
odoo/addons/maintenance_stock/static/img/toner.png
odoo/addons/maintenance_stock/tests/__init__.py
odoo/addons/maintenance_stock/tests/test_maintenance_stock.py
odoo/addons/maintenance_stock/views/maintenance_equipment_views.xml
odoo/addons/maintenance_stock/views/maintenance_request_views.xml
odoo/addons/maintenance_stock/views/stock_move_line_views.xml
odoo/addons/maintenance_stock/views/stock_move_views.xml
odoo/addons/maintenance_stock/views/stock_picking_views.xml
odoo13_addon_maintenance_stock-13.0.1.0.1.dev5.dist-info/METADATA
odoo13_addon_maintenance_stock-13.0.1.0.1.dev5.dist-info/WHEEL
odoo13_addon_maintenance_stock-13.0.1.0.1.dev5.dist-info/top_level.txt
odoo13_addon_maintenance_stock-13.0.1.0.1.dev5.dist-info/RECORD
